{
    "key": "group_59ed528948af8",
    "title": "Services - Industry Expertise & Contact Form",
    "fields": [
        {
            "key": "field_59ed5327775d3",
            "label": "Show this section",
            "name": "show_this_section",
            "type": "checkbox",
            "instructions": "",
            "required": 0,
            "conditional_logic": 0,
            "wrapper": {
                "width": "",
                "class": "",
                "id": ""
            },
            "choices": {
                "Yes": "Yes",
                "No": "No"
            },
            "allow_custom": 0,
            "save_custom": 0,
            "default_value": [
                "Yes"
            ],
            "layout": "horizontal",
            "toggle": 0,
            "return_format": "value"
        },
        {
            "key": "field_59ed528d775d1",
            "label": "Industry Expertise Intro",
            "name": "industry_expertise_intro",
            "type": "wysiwyg",
            "instructions": "",
            "required": 0,
            "conditional_logic": 0,
            "wrapper": {
                "width": "",
                "class": "",
                "id": ""
            },
            "default_value": "",
            "tabs": "all",
            "toolbar": "full",
            "media_upload": 1,
            "delay": 0
        },
        {
            "key": "field_59ed52dc775d2",
            "label": "Industry Expertise Posts",
            "name": "industry_expertise_posts",
            "type": "post_object",
            "instructions": "",
            "required": 0,
            "conditional_logic": 0,
            "wrapper": {
                "width": "",
                "class": "",
                "id": ""
            },
            "post_type": [
                "industryexpertise"
            ],
            "taxonomy": [],
            "allow_null": 0,
            "multiple": 1,
            "return_format": "id",
            "ui": 1
        },
        {
            "key": "field_59ed777538121",
            "label": "Show Testimonial Section?",
            "name": "show_testimonial_section",
            "type": "checkbox",
            "instructions": "",
            "required": 0,
            "conditional_logic": 0,
            "wrapper": {
                "width": "",
                "class": "",
                "id": ""
            },
            "choices": {
                "Yes": "Yes"
            },
            "allow_custom": 0,
            "save_custom": 0,
            "default_value": [],
            "layout": "horizontal",
            "toggle": 0,
            "return_format": "value"
        },
        {
            "key": "field_59ed78ae42c9d",
            "label": "Contact Headings",
            "name": "contact_headings",
            "type": "wysiwyg",
            "instructions": "",
            "required": 0,
            "conditional_logic": 0,
            "wrapper": {
                "width": "",
                "class": "",
                "id": ""
            },
            "default_value": "",
            "tabs": "all",
            "toolbar": "full",
            "media_upload": 0,
            "delay": 0
        },
        {
            "key": "field_59ed78d942c9e",
            "label": "Contact Short Code",
            "name": "contact_short_code",
            "type": "text",
            "instructions": "",
            "required": 0,
            "conditional_logic": 0,
            "wrapper": {
                "width": "",
                "class": "",
                "id": ""
            },
            "default_value": "",
            "placeholder": "",
            "prepend": "",
            "append": "",
            "maxlength": ""
        }
    ],
    "location": [
        [
            {
                "param": "post_type",
                "operator": "==",
                "value": "page"
            },
            {
                "param": "page",
                "operator": "==",
                "value": "8"
            }
        ]
    ],
    "menu_order": 0,
    "position": "normal",
    "style": "default",
    "label_placement": "top",
    "instruction_placement": "label",
    "hide_on_screen": "",
    "active": 1,
    "description": "",
    "modified": 1508735212
}